kahi_minciencias_opendata_affiliations/Kahi_minciencias_opendata_affiliations.py
kahi_minciencias_opendata_affiliations/__init__.py
kahi_minciencias_opendata_affiliations/_version.py
Kahi_minciencias_opendata_affiliations-0.1.3.dist-info/LICENSE
Kahi_minciencias_opendata_affiliations-0.1.3.dist-info/METADATA
Kahi_minciencias_opendata_affiliations-0.1.3.dist-info/WHEEL
Kahi_minciencias_opendata_affiliations-0.1.3.dist-info/top_level.txt
Kahi_minciencias_opendata_affiliations-0.1.3.dist-info/RECORD
