Metadata-Version: 2.2
Name: Kahi_minciencias_opendata_affiliations
Version: 0.1.3
Summary: Kahi plugin minciencias_opendata_affiliations
Home-page: https://github.com/colav/Kahi_plugins
Author: Colav
Author-email: colav@udea.edu.co
License: BSD
License-File: LICENSE
Requires-Dist: kahi
Requires-Dist: pymongo
Requires-Dist: thefuzz
Requires-Dist: unidecode
Dynamic: author
Dynamic: author-email
Dynamic: description
Dynamic: description-content-type
Dynamic: home-page
Dynamic: license
Dynamic: requires-dist
Dynamic: summary
